{
    "428592574723522560": {
        "economy": {
            "pockets": 1313,
            "bank": 0,
            "total": 1313,
            "net": 1313
        },
        "other": {
            "daily": 0
        },
        "timer": {
            "daily": "30/06/2022"
        },
        "statistic": {
            "daily": {
                "times": 1,
                "earned": 1313,
                "streak": 1
            },
            "gamble": {
                "times": 0,
                "earned": 0,
                "lost": 0
            },
            "inventoryOpened": 0
        },
        "debug": false
    }
}